adbdgl_adapter/__init__.py
adbdgl_adapter/abc.py
adbdgl_adapter/adapter.py
adbdgl_adapter/controller.py
adbdgl_adapter/encoders.py
adbdgl_adapter/exceptions.py
adbdgl_adapter/typings.py
adbdgl_adapter/utils.py
adbdgl_adapter-3.0.1.dist-info/LICENSE
adbdgl_adapter-3.0.1.dist-info/METADATA
adbdgl_adapter-3.0.1.dist-info/WHEEL
adbdgl_adapter-3.0.1.dist-info/top_level.txt
adbdgl_adapter-3.0.1.dist-info/RECORD
